substring_match-0.1.3.dist-info/METADATA
substring_match-0.1.3.dist-info/WHEEL
substring_match/__init__.py
substring_match/substring_match.abi3.so
substring_match-0.1.3.dist-info/RECORD
