Metadata-Version: 2.1
Name: substring-match
Version: 0.1.3
Keywords: substring,string,match,search,suffixtree,suffixarray,suffix,array,tree
Home-Page: https://github.com/Carbon225/substring-match-rs
Author: Carbon225 <carbon225@proton.me>
Author-email: Carbon225 <carbon225@proton.me>
License: MIT
Project-URL: Source Code, https://github.com/Carbon225/substring-match-rs.git
